reldplayer/__init__.py
reldplayer/utils.py
reldplayer/_internal/wndCtrl.py
reldplayer/ext/window.py
reldplayer/ext/windowCollection.py
reldplayer/ext/windowMgr.py
reldplayer/overloads/__init__.py
reldplayer/overloads/load.py
reldplayer/shell/__init__.py
reldplayer-1.0.1.dist-info/METADATA
reldplayer-1.0.1.dist-info/WHEEL
reldplayer-1.0.1.dist-info/entry_points.txt
reldplayer-1.0.1.dist-info/licenses/LICENSE
reldplayer-1.0.1.dist-info/RECORD
