Metadata-Version: 2.4
Name: reldplayer
Version: 1.0.1
Summary: a superset to pyldplayer
Author-email: ZackaryW <36378555+ZackaryW@users.noreply.github.com>
License-File: LICENSE
Requires-Python: >=3.8
Requires-Dist: click>=8.1.7
Requires-Dist: pygetwindow>=0.0.9
Requires-Dist: pyldplayer>=4.1.6
Provides-Extra: full
Requires-Dist: psutil>=6.1.0; extra == 'full'
Requires-Dist: pyautogui>=0.9.54; extra == 'full'
Requires-Dist: screeninfo>=0.8.1; extra == 'full'
